<?xml version="1.0"  encoding="utf-8" ?>
<hibernate-mapping xmlns="urn:nhibernate-mapping-2.2" assembly="LocalEntity" namespace="LocalEntity.Entities">
	<class name="POINTTARGET" table="POINTTARGET">
		<id name="ID" column="ID" type="int" unsaved-value="0">
      <generator class="increment" />
    </id>      		
		<property name="TARGETCODE" column="TARGETCODE" type="string"  />
		<property name="LONGTITUDE" column="LONGTITUDE" type="string"  />
		<property name="LATITUDE" column="LATITUDE" type="string"  />
		<property name="PRIORITY" column="PRIORITY" type="string"  />
		<property name="DETECTNUM" column="DETECTNUM" type="string"  />
		<property name="PROPOSETIME" column="PROPOSETIME" type="string"  />
		<property name="PROPOSEPERSON" column="PROPOSEPERSON" type="string"  />
		<property name="DETECTTIME" column="DETECTTIME" type="string"  />
		<property name="ALLOWABLEVIRATION" column="ALLOWABLEVIRATION" type="string"  />
				
	</class>
</hibernate-mapping>